site2hdd/LICENSE
site2hdd/README.MD
site2hdd/__init__.py
site2hdd/requirements.txt
site2hdd/thirdparty.json
site2hdd-0.15.dist-info/LICENSE.rst
site2hdd-0.15.dist-info/METADATA
site2hdd-0.15.dist-info/WHEEL
site2hdd-0.15.dist-info/top_level.txt
site2hdd-0.15.dist-info/RECORD
