Metadata-Version: 2.1
Name: site2hdd
Version: 0.15
Summary: Download sites with public proxies - threading
Home-page: https://github.com/hansalemaos/site2hdd
Author: Johannes Fischer
Author-email: <aulasparticularesdealemaosp@gmail.com>
License: MIT
Keywords: download,scrape,site
Classifier: Development Status :: 4 - Beta
Classifier: Programming Language :: Python :: 3 :: Only
Classifier: Programming Language :: Python :: 3.9
Classifier: Topic :: Scientific/Engineering :: Visualization
Classifier: Topic :: Software Development :: Libraries :: Python Modules
Classifier: Topic :: Text Editors :: Text Processing
Classifier: Topic :: Text Processing :: General
Classifier: Topic :: Text Processing :: Indexing
Classifier: Topic :: Text Processing :: Filters
Classifier: Topic :: Utilities
License-File: LICENSE.rst
Requires-Dist: a-pandas-ex-apply-ignore-exceptions
Requires-Dist: a-pandas-ex-horizontal-explode
Requires-Dist: beautifulsoup4
Requires-Dist: check-if-nan
Requires-Dist: cprinter
Requires-Dist: flatten-any-dict-iterable-or-whatsoever
Requires-Dist: flatten-everything
Requires-Dist: freeproxydownloader
Requires-Dist: keyboard
Requires-Dist: kthread-sleep
Requires-Dist: numba
Requires-Dist: openpyxl
Requires-Dist: pandas
Requires-Dist: regex
Requires-Dist: requests
Requires-Dist: threadingbatch
Requires-Dist: tolerant-isinstance
Requires-Dist: touchtouch
Requires-Dist: url-analyzer
Requires-Dist: windows-filepath
